p_files/__init__.py
p_files/json.py
p_files-0.0.7.dist-info/METADATA
p_files-0.0.7.dist-info/WHEEL
p_files-0.0.7.dist-info/top_level.txt
p_files-0.0.7.dist-info/RECORD
