Metadata-Version: 2.1
Name: p-files
Version: 0.0.7
Summary: A Python package for file operations.
Home-page: https://github.com/Glawnn/p_files
Author: Gael
Author-email: 
License: UNKNOWN
Project-URL: Source, https://github.com/Glawnn/p_files
Platform: UNKNOWN
Requires-Dist: setuptools
Requires-Dist: pytest
Requires-Dist: pylint
Requires-Dist: twine
Requires-Dist: wheel
